{
  "id": "intro",
  "title": "Welcome to Presetter",
  "description": "Configuration Management That Scales With Your Projects",
  "source": "@site/docs/intro.md",
  "sourceDirName": ".",
  "slug": "/",
  "permalink": "/presetter/docs/",
  "draft": false,
  "unlisted": false,
  "editUrl": "https://github.com/alvis/presetter/tree/master/website/docs/intro.md",
  "tags": [],
  "version": "current",
  "lastUpdatedBy": null,
  "lastUpdatedAt": null,
  "sidebarPosition": 1,
  "frontMatter": {
    "sidebar_position": 1,
    "slug": "/",
    "title": "Welcome to Presetter"
  },
  "sidebar": "tutorialSidebar",
  "next": {
    "title": "Introduction",
    "permalink": "/presetter/docs/introduction/"
  }
}